fhm_unittest/__init__.py
fhm_unittest-1.0.1.dist-info/LICENSE
fhm_unittest-1.0.1.dist-info/METADATA
fhm_unittest-1.0.1.dist-info/WHEEL
fhm_unittest-1.0.1.dist-info/top_level.txt
fhm_unittest-1.0.1.dist-info/RECORD
