Metadata-Version: 2.1
Name: fhm-unittest
Version: 1.0.1
Summary: A package for unittest
Home-page: https://github.com/pypa/sampleproject
Author: Farah Al Fahim
Author-email: s.m.farah.al.fahim@g.bracu.ac.bd
Project-URL: Bug Tracker, https://github.com/pypa/sampleproject/issues
Classifier: Programming Language :: Python :: 3
Classifier: License :: OSI Approved :: MIT License
Classifier: Operating System :: OS Independent
Requires-Python: >=3.6
License-File: LICENSE
